tests/__init__.py
tests/test_client_check.py
tests/test_core_check.py
tests/test_core_exclude.py
tests/test_core_fileproc.py
tests/test_core_urlproc.py
tests/test_main_github.py
tests/test_main_utils.py
urlchecker/__init__.py
urlchecker/logger.py
urlchecker/version.py
urlchecker/client/__init__.py
urlchecker/client/check.py
urlchecker/core/__init__.py
urlchecker/core/check.py
urlchecker/core/exclude.py
urlchecker/core/fileproc.py
urlchecker/core/urlmarker.py
urlchecker/core/urlproc.py
urlchecker/core/webdriver.py
urlchecker/core/worker.py
urlchecker/main/__init__.py
urlchecker/main/github.py
urlchecker/main/utils.py
urlchecker-0.0.35.dist-info/LICENSE
urlchecker-0.0.35.dist-info/LICENSE.chromedriver
urlchecker-0.0.35.dist-info/METADATA
urlchecker-0.0.35.dist-info/WHEEL
urlchecker-0.0.35.dist-info/entry_points.txt
urlchecker-0.0.35.dist-info/top_level.txt
urlchecker-0.0.35.dist-info/RECORD
