Metadata-Version: 2.1
Name: urlchecker
Version: 0.0.35
Summary: tool to collect and validate urls over static files (code and documentation)
Home-page: http://www.github.com/urlstechie/urlchecker-python
Author: Ayoub Malek, Vanessa Sochat
Author-email: superkogito@gmail.com, vsochat@stanford.edu
Maintainer: Ayoub Malek, Vanessa Sochat
Maintainer-email: superkogito@gmail.com, vsochat@stanford.edu
License: LICENSE
Keywords: urls,static checking,checking,validation
Classifier: Intended Audience :: Developers
Classifier: License :: OSI Approved :: MIT License
Classifier: Programming Language :: Python
Classifier: Topic :: Software Development
Classifier: Topic :: Scientific/Engineering
Classifier: Operating System :: Unix
Classifier: Programming Language :: Python :: 3.7
License-File: LICENSE
License-File: LICENSE.chromedriver
Requires-Dist: requests >=2.18.4
Requires-Dist: fake-useragent >=0.1.13
Requires-Dist: selenium
Provides-Extra: all
Requires-Dist: requests >=2.18.4 ; extra == 'all'
Requires-Dist: fake-useragent >=0.1.13 ; extra == 'all'
Requires-Dist: selenium ; extra == 'all'
Requires-Dist: pytest >=4.6.2 ; extra == 'all'
